{
  "slug": "hello-world",
  "entries": [
    {
      "question": "A question?",
      "answer": "An answer!",
      "feature": "adequacy",
      "shortDescription": "test",
      "tagSlugs": [

      ]
    },
    {
      "answer": "`This is a test.`\n\n* 1\n* 2\n* 3\n\n1. A\n2. B\n3. C\n\n```\nThis is a test.\n```\n\n[Home Link](/#!)\n\n[](/#!)\n\n![network 360 logo](/cms/cms-assets/media/header_logo.png \"N360\")\n\n[](/#!)",
      "question": "Test",
      "feature": "qa_mode",
      "shortDescription": "test",
      "tagSlugs": [

      ]
    },
    {
      "question": "CMS",
      "answer": "2024\n\n<help-video data-id='test-video-with-no-section-and-subsection'></help-video>",
      "feature": "assess_markets",
      "shortDescription": "Netlify",
      "tagSlugs": [
        "rank-networks",
        "look-up-a-provider"
      ]
    }
  ],
  "sectionSlug": "oe-test",
  "title": "Hello World!",
  "feature": "qa_mode",
  "shortDescription": "Test",
  "body": "This is for testing."
}